CHANGELOG.md
CONTRIBUTING.md
LICENSE
MANIFEST.in
README.rst
requirements.txt
setup.py
ChemDataExtractor_IDE.egg-info/PKG-INFO
ChemDataExtractor_IDE.egg-info/SOURCES.txt
ChemDataExtractor_IDE.egg-info/dependency_links.txt
ChemDataExtractor_IDE.egg-info/entry_points.txt
ChemDataExtractor_IDE.egg-info/not-zip-safe
ChemDataExtractor_IDE.egg-info/requires.txt
ChemDataExtractor_IDE.egg-info/top_level.txt
chemdataextractor/__init__.py
chemdataextractor/config.py
chemdataextractor/data.py
chemdataextractor/errors.py
chemdataextractor/model.py
chemdataextractor/utils.py
chemdataextractor/biblio/__init__.py
chemdataextractor/biblio/bibtex.py
chemdataextractor/biblio/person.py
chemdataextractor/biblio/xmp.py
chemdataextractor/cli/__init__.py
chemdataextractor/cli/cem.py
chemdataextractor/cli/chemdner.py
chemdataextractor/cli/cluster.py
chemdataextractor/cli/config.py
chemdataextractor/cli/data.py
chemdataextractor/cli/dict.py
chemdataextractor/cli/evaluate.py
chemdataextractor/cli/pos.py
chemdataextractor/cli/tokenize.py
chemdataextractor/doc/__init__.py
chemdataextractor/doc/document.py
chemdataextractor/doc/element.py
chemdataextractor/doc/figure.py
chemdataextractor/doc/meta.py
chemdataextractor/doc/table.py
chemdataextractor/doc/text.py
chemdataextractor/nlp/__init__.py
chemdataextractor/nlp/abbrev.py
chemdataextractor/nlp/cem.py
chemdataextractor/nlp/corpus.py
chemdataextractor/nlp/lexicon.py
chemdataextractor/nlp/pos.py
chemdataextractor/nlp/tag.py
chemdataextractor/nlp/tokenize.py
chemdataextractor/parse/__init__.py
chemdataextractor/parse/actions.py
chemdataextractor/parse/base.py
chemdataextractor/parse/cem.py
chemdataextractor/parse/common.py
chemdataextractor/parse/context.py
chemdataextractor/parse/elements.py
chemdataextractor/parse/ir.py
chemdataextractor/parse/microscopy.py
chemdataextractor/parse/mp.py
chemdataextractor/parse/nmr.py
chemdataextractor/parse/table.py
chemdataextractor/parse/tg.py
chemdataextractor/parse/uvvis.py
chemdataextractor/reader/__init__.py
chemdataextractor/reader/acs.py
chemdataextractor/reader/base.py
chemdataextractor/reader/cssp.py
chemdataextractor/reader/elsevier.py
chemdataextractor/reader/markup.py
chemdataextractor/reader/nlm.py
chemdataextractor/reader/pdf.py
chemdataextractor/reader/plaintext.py
chemdataextractor/reader/rsc.py
