Metadata-Version: 1.1
Name: ChemDataExtractor-IDE
Version: 1.3.2
Summary: A toolkit for extracting chemical information from the scientific literature.
Home-page: https://github.com/edbeard/chemdataextractor-ide.git
Author: Matt Swain, Ed Beard
Author-email: m.swain@me.com, ed.beard94@gmail.com
License: MIT
Download-URL: https://github.com/edbeard/chemdataextractor-ide/archive/1.3.2.tar.gz
Keywords: text-mining mining chemistry cheminformatics nlp html xml science scientific
Platform: UNKNOWN
Classifier: Intended Audience :: Developers
Classifier: Intended Audience :: Science/Research
Classifier: License :: OSI Approved :: MIT License
Classifier: Operating System :: OS Independent
Classifier: Topic :: Internet :: WWW/HTTP :: Indexing/Search
Classifier: Topic :: Scientific/Engineering
Classifier: Topic :: Scientific/Engineering :: Bio-Informatics
Classifier: Topic :: Scientific/Engineering :: Chemistry
Classifier: Topic :: Text Processing
Classifier: Topic :: Text Processing :: Linguistic
Classifier: Topic :: Text Processing :: Markup :: HTML
